_hgdb.cpython-36m-x86_64-linux-gnu.so
hgdb/client.py
hgdb/db.py
hgdb/__init__.py
hgdb/symbol.py
hgdb-0.1.4.dist-info/WHEEL
hgdb-0.1.4.dist-info/top_level.txt
hgdb-0.1.4.dist-info/RECORD
hgdb-0.1.4.dist-info/METADATA
hgdb-0.1.4.data/scripts/toml2hgdb
hgdb.libs/libsqlite3-0042ad0d.so.0.8.6
