Metadata-Version: 2.1
Name: hgdb
Version: 0.1.4
Summary: UNKNOWN
Home-page: https://github.com/Kuree/hgdb
Author: Keyi Zhang
Author-email: keyi@cs.stanford.edu
License: UNKNOWN
Platform: UNKNOWN
Requires-Python: >=3.6
Provides-Extra: all
Requires-Dist: websockets ; extra == 'all'
Requires-Dist: toml ; extra == 'all'
Provides-Extra: client
Requires-Dist: websockets ; extra == 'client'
Provides-Extra: toml
Requires-Dist: toml ; extra == 'toml'
